{"_default": {"1": {"deps": [], "output": {"null": []}, "cmd": ["julia", "calibrate_model.jl", "2"], "start_time": "26/10/2023 14:30:02", "finish_time": "26/10/2023 14:30:04"}, "2": {"deps": [], "output": {"null": []}, "cmd": ["julia", "calibrate_model.jl", "3"], "start_time": "26/10/2023 14:30:02", "finish_time": "26/10/2023 14:30:04"}, "3": {"deps": [], "output": {"null": []}, "cmd": ["julia", "calibrate_model.jl", "4"], "start_time": "26/10/2023 14:30:03", "finish_time": "26/10/2023 14:30:05"}, "4": {"deps": [], "output": {"null": []}, "cmd": ["julia", "calibrate_model.jl", "5"], "start_time": "26/10/2023 14:30:03", "finish_time": "26/10/2023 14:30:05"}, "5": {"deps": [], "output": {"null": []}, "cmd": ["julia", "calibrate_model.jl", "5"], "start_time": "26/10/2023 15:30:43", "finish_time": "26/10/2023 15:31:44"}, "6": {"deps": [], "output": {"null": []}, "cmd": ["julia", "calibrate_model.jl", "4"], "start_time": "26/10/2023 15:30:42", "finish_time": "26/10/2023 15:31:44"}, "7": {"deps": [], "output": {"null": []}, "cmd": ["julia", "calibrate_model.jl", "2"], "start_time": "26/10/2023 15:30:42", "finish_time": "26/10/2023 15:31:45"}, "8": {"deps": [], "output": {"null": []}, "cmd": ["julia", "calibrate_model.jl", "2"], "start_time": "26/10/2023 15:35:12", "finish_time": "26/10/2023 15:36:13"}, "9": {"deps": [], "output": {"null": []}, "cmd": ["julia", "calibrate_model.jl", "4"], "start_time": "26/10/2023 15:35:13", "finish_time": "26/10/2023 15:36:14"}, "10": {"deps": [], "output": {"null": []}, "cmd": ["julia", "calibrate_model.jl", "5"], "start_time": "26/10/2023 15:35:13", "finish_time": "26/10/2023 15:36:19"}, "11": {"deps": [], "output": {"null": []}, "cmd": ["julia", "init_output.jl"], "start_time": "26/10/2023 15:37:35", "finish_time": "26/10/2023 15:37:35"}, "12": {"deps": [], "output": {"null": []}, "cmd": ["julia", "calibrate_model.jl", "5"], "start_time": "26/10/2023 15:37:36", "finish_time": "26/10/2023 15:38:36"}, "13": {"deps": [], "output": {"null": []}, "cmd": ["julia", "calibrate_model.jl", "2"], "start_time": "26/10/2023 15:37:35", "finish_time": "26/10/2023 15:38:36"}, "14": {"deps": [], "output": {"null": []}, "cmd": ["julia", "calibrate_model.jl", "4"], "start_time": "26/10/2023 15:37:36", "finish_time": "26/10/2023 15:38:43"}, "15": {"deps": [], "output": {"null": []}, "cmd": ["julia", "init_output.jl"], "start_time": "26/10/2023 15:46:18", "finish_time": "26/10/2023 15:46:19"}, "16": {"deps": [], "output": {"null": []}, "cmd": ["julia", "calibrate_model.jl", "5"], "start_time": "26/10/2023 15:46:20", "finish_time": "26/10/2023 15:47:26"}, "17": {"deps": [], "output": {"null": []}, "cmd": ["julia", "calibrate_model.jl", "4"], "start_time": "26/10/2023 15:46:19", "finish_time": "26/10/2023 15:47:26"}, "18": {"deps": [], "output": {"null": []}, "cmd": ["julia", "calibrate_model.jl", "2"], "start_time": "26/10/2023 15:46:19", "finish_time": "26/10/2023 15:47:34"}, "19": {"deps": [], "output": {"null": []}, "cmd": ["julia", "init_output.jl"], "start_time": "26/10/2023 15:54:28", "finish_time": "26/10/2023 15:54:42"}, "20": {"deps": [], "output": {"null": []}, "cmd": ["julia", "calibrate_model.jl", "2"], "start_time": "26/10/2023 15:54:43", "finish_time": "26/10/2023 15:56:24"}, "21": {"deps": [], "output": {"null": []}, "cmd": ["julia", "calibrate_model.jl", "4"], "start_time": "26/10/2023 15:54:43", "finish_time": "26/10/2023 15:56:24"}, "22": {"deps": [], "output": {"null": []}, "cmd": ["julia", "calibrate_model.jl", "5"], "start_time": "26/10/2023 15:54:43", "finish_time": "26/10/2023 15:56:24"}, "23": {"deps": [], "output": {"null": []}, "cmd": ["julia", "combine_output.jl"], "start_time": "26/10/2023 15:56:24", "finish_time": "26/10/2023 15:56:54"}}}